anodilib/.DS_Store
anodilib/algorithm/AllFalse.py
anodilib/algorithm/AllTrue.py
anodilib/algorithm/AnoFormer.py
anodilib/algorithm/IsolationForest.py
anodilib/algorithm/MTAD_GAT.py
anodilib/algorithm/ModifiedLSTM.py
anodilib/algorithm/NPRandom.py
anodilib/algorithm/Random.py
anodilib/algorithm/TCNAE.py
anodilib/algorithm/TranVAE.py
anodilib/algorithm/__init__.py
anodilib/algorithm/algorithm.py
anodilib/algorithm/callback.py
anodilib/algorithm/learner.py
anodilib/algorithm/loss.py
anodilib/algorithm/spot.py
anodilib/algorithm/utils.py
anodilib/benchmark/__init__.py
anodilib/benchmark/benchmark.py
anodilib/benchmark/core.py
anodilib/benchmark/modelWrapper.py
anodilib/benchmark/param.py
anodilib/benchmark/paramSet.py
anodilib/benchmark/parameterSearch.py
anodilib/benchmark/plot.py
anodilib/data/DatasetSpecification.py
anodilib/data/ECG200.txt
anodilib/data/__init__.py
anodilib/data/data/ECG200_TEST.txt
anodilib/data/data/ECG200_TRAIN.txt
anodilib/data/data/WADI.A2_19_Nov_2019_WADI_attackdataLABLE.csv
anodilib/data/dataset.py
anodilib/data/download.py
anodilib/data/preprocessing.py
anodilib/data/utils.py
anodilib/interpretation/__init__.py
anodilib/interpretation/dev-README.md
anodilib/interpretation/utils.py
anodilib/metrics/__init__.py
anodilib/metrics/cmetrics.py
anodilib/metrics/dev-README.md
anodilib/metrics/pa/pointAdjustment.py
anodilib/metrics/utils.py
anodilib/model/__init__.py
anodilib/model/ano_former.py
anodilib/model/dev-README.md
anodilib/model/lstm.py
anodilib/model/mtad_gat.py
anodilib/model/tcnae.py
anodilib/model/tranvae.py
anodilib/model/utils.py
anodilib/tests/captum_demo_feature_ablation.ipynb
anodilib/tests/captum_demo_integrated_gradients.ipynb
anodilib/tests/test_ano_former.py
anodilib/tests/test_isoforest.py
anodilib/tests/test_load_save.py
anodilib/tests/test_lstm.py
anodilib/tests/test_mtad_gat.py
anodilib/tests/test_tcn.py
anodilib/tests/test_tranvae.py
anodilib/visualization/__init__.py
anodilib/visualization/data_viewer.py
anodilib-0.1.5.dist-info/METADATA
anodilib-0.1.5.dist-info/WHEEL
anodilib-0.1.5.dist-info/RECORD
